minder/research_data_snapshots/__init__.py
minder/research_data_snapshots/__main__.py
minder/research_data_snapshots/py.typed
minder_research_data_snapshots-0.23.0.dist-info/METADATA
minder_research_data_snapshots-0.23.0.dist-info/WHEEL
minder_research_data_snapshots-0.23.0.dist-info/top_level.txt
minder_research_data_snapshots-0.23.0.dist-info/RECORD
