Metadata-Version: 2.4
Name: minder.research-data-snapshots
Version: 0.23.0
Requires-Python: >=3.10
Requires-Dist: platformdirs~=4.0
Requires-Dist: requests~=2.0
Requires-Dist: tqdm~=4.0
Provides-Extra: lint
Requires-Dist: ruff; extra == "lint"
Provides-Extra: typecheck
Requires-Dist: pyright; extra == "typecheck"
Provides-Extra: dev
Requires-Dist: minder.research-data-snapshots[lint,typecheck]; extra == "dev"
Provides-Extra: csv
Requires-Dist: pyarrow>=13; extra == "csv"
Requires-Dist: pandas~=2.0; extra == "csv"
